.gitignore
Cargo.lock
Cargo.toml
LICENSE
README.md
pyproject.toml
rustfmt.toml
setup.py
.github/dependabot.yml
.github/workflows/check-package-install.yml
.github/workflows/pypi-publish.yml
.github/workflows/rust.yml
.github/workflows/rustfmt.yml
others/persia-common-benchmark/Cargo.toml
others/persia-common-benchmark/benches/memcpy.rs
others/persia-common-benchmark/benches/serialize_inf_request.rs
others/persia-common-benchmark/src/lib.rs
persia-embedding-config/Cargo.toml
persia-embedding-config/examples/global_config.yaml
persia-embedding-config/src/feature_config.rs
persia-embedding-config/src/lib.rs
persia-embedding-datatypes/Cargo.toml
persia-embedding-datatypes/src/lib.rs
persia-embedding-datatypes/src/optim.rs
persia-embedding-holder/Cargo.toml
persia-embedding-holder/src/lib.rs
persia-embedding-py-client-sharded-server/Cargo.toml
persia-embedding-py-client-sharded-server/build.rs
persia-embedding-py-client-sharded-server/src/backward.rs
persia-embedding-py-client-sharded-server/src/data.rs
persia-embedding-py-client-sharded-server/src/forward.rs
persia-embedding-py-client-sharded-server/src/lib.rs
persia-embedding-py-client-sharded-server/src/optim.rs
persia-embedding-py-client-sharded-server/src/utils.rs
persia-embedding-py-client-sharded-server/src/cuda/cuda_event_pool.rs
persia-embedding-py-client-sharded-server/src/cuda/cuda_memory_pool.rs
persia-embedding-py-client-sharded-server/src/cuda/cuda_stream_pool.rs
persia-embedding-py-client-sharded-server/src/cuda/mod.rs
persia-embedding-py-client-sharded-server/src/cuda/pinned_memory_pool.rs
persia-embedding-py-client-sharded-server/src/cuda/utils.rs
persia-embedding-sharded-server/Cargo.toml
persia-embedding-sharded-server/build.rs
persia-embedding-sharded-server/benches/middleware_config.yaml
persia-embedding-sharded-server/benches/serialize_vec_f16.rs
persia-embedding-sharded-server/benches/serialize_vec_f32.rs
persia-embedding-sharded-server/benches/sharded_server.rs
python/persia_embedding_py_client_sharded_server.egg-info/PKG-INFO
python/persia_embedding_py_client_sharded_server.egg-info/SOURCES.txt
python/persia_embedding_py_client_sharded_server.egg-info/dependency_links.txt
python/persia_embedding_py_client_sharded_server.egg-info/not-zip-safe
python/persia_embedding_py_client_sharded_server.egg-info/top_level.txt