Metadata-Version: 2.1
Name: persia-embedding-py-client-sharded-server
Version: 0.1.dev25
Summary: Core Python binding for PersiaML.
Home-page: https://github.com/PersiaML/PersiaML-server
Author: Kuaishou AI Platform
Author-email: admin@mail.xrlian.com
License: UNKNOWN
Platform: UNKNOWN
Requires-Python: >=3.6
License-File: LICENSE
